collective.complexrecordsproxy-1.1-py3.10-nspkg.pth
collective/complexrecordsproxy/__init__.py
collective/complexrecordsproxy/complexrecordsproxy.py
collective.complexrecordsproxy-1.1.dist-info/METADATA
collective.complexrecordsproxy-1.1.dist-info/WHEEL
collective.complexrecordsproxy-1.1.dist-info/entry_points.txt
collective.complexrecordsproxy-1.1.dist-info/namespace_packages.txt
collective.complexrecordsproxy-1.1.dist-info/top_level.txt
collective.complexrecordsproxy-1.1.dist-info/RECORD
