Metadata-Version: 2.1
Name: collective.complexrecordsproxy
Version: 1.1
Summary: Providing a proxy class for plone.registry allowing IObject fields to be stored as separate records using the plone.registry collection support.
Home-page: http://pypi.python.org/pypi/collective.complexrecordsproxy
Author: Sune Broendum Woeller
Author-email: sune@woeller.dk
License: GPLv2+
Keywords: configuration registry
Platform: UNKNOWN
Classifier: Framework :: Plone
Classifier: Framework :: Plone :: 4.3
Classifier: Framework :: Plone :: 5.0
Classifier: Framework :: Plone :: 5.1
Classifier: Framework :: Plone :: 5.2
Classifier: Framework :: Plone :: 6.0
Classifier: Framework :: Zope2
Classifier: Programming Language :: Python
Classifier: Programming Language :: Python :: 2.7
Classifier: Programming Language :: Python :: 3
Classifier: Programming Language :: Python :: 3.7
Classifier: Programming Language :: Python :: 3.8
Requires-Dist: setuptools
Requires-Dist: plone.registry (>=1.0)
